src/__init__.py
src/calais_weather.py
src/history.py
src/logging_setup.py
src/main.py
src/persistence.py
src/router.py
src/agents/__init__.py
src/agents/bart.py
src/agents/bernie.py
src/agents/blanca.py
src/agents/bukowski.py
src/agents/bukowski_ledger.py
src/agents/hermes.py
src/agents/jb.py
src/agents/llm_client.py
src/config/__init__.py
src/config/loader.py
src/config/prompts.yaml
src/schemas/__init__.py
src/schemas/message.py
src/tests/test_agent_behavior.py
src/tests/test_bart.py
src/tests/test_bernie.py
src/tests/test_blanca.py
src/tests/test_bukowski.py
src/tests/test_config.py
src/tests/test_hermes.py
src/tests/test_history.py
src/tests/test_integration.py
src/tests/test_jb.py
src/tests/test_ledger.py
src/tests/test_properties.py
src/tests/test_router_error_handling.py
src/tests/test_router_integration.py
src/tests/test_router_unit.py
src/tests/test_router_unit_pure.py
lpbd-0.1.0.dist-info/METADATA
lpbd-0.1.0.dist-info/WHEEL
lpbd-0.1.0.dist-info/licenses/LICENSE
lpbd-0.1.0.dist-info/RECORD
