Metadata-Version: 2.4
Name: lpbd
Version: 0.1.0
Summary: Le Pale Blue Dot - A multi-agent conversational AI system set in a noir bar
Project-URL: Homepage, https://github.com/FSHolmberg/Le-Pale-Blue-Dot
Project-URL: Repository, https://github.com/FSHolmberg/Le-Pale-Blue-Dot
Project-URL: Issues, https://github.com/FSHolmberg/Le-Pale-Blue-Dot/issues
Author-email: Fredrik Holmberg <fsholmberg@gmail.com>
License: MIT
License-File: LICENSE
Keywords: agents,ai,anthropic,claude,conversational-ai
Classifier: Development Status :: 3 - Alpha
Classifier: Intended Audience :: Developers
Classifier: License :: OSI Approved :: MIT License
Classifier: Programming Language :: Python :: 3
Classifier: Programming Language :: Python :: 3.10
Classifier: Programming Language :: Python :: 3.11
Classifier: Programming Language :: Python :: 3.12
Requires-Python: >=3.10
Requires-Dist: anthropic>=0.40.0
Requires-Dist: pydantic>=2.0.0
Requires-Dist: python-dotenv>=1.0.0
Requires-Dist: pyyaml>=6.0
Requires-Dist: requests>=2.31.0
Provides-Extra: dev
Requires-Dist: hypothesis>=6.100.0; extra == 'dev'
Requires-Dist: pytest-cov>=4.0.0; extra == 'dev'
Requires-Dist: pytest>=7.0.0; extra == 'dev'
